proteus/__init__.py
proteus/api.py
proteus/bin/runs_workflow.py
proteus/bucket.py
proteus/calculator/__init__.py
proteus/calculator/calculator.py
proteus/calculator/grammar.py
proteus/calculator/operations.py
proteus/calculator/parser.py
proteus/config.py
proteus/logger.py
proteus/logging.ini
proteus/oidc.py
proteus/pubsub.py
proteus/reporting.py
proteus/runs.py
proteus/safe/__init__.py
proteus/safe/common.py
proteus/safe/cypher.py
proteus/safe/decypher.py
proteus/stats.py
proteus/utils.py
proteus/vault.py
proteus_runtime-0.6.0.dist-info/LICENSE
proteus_runtime-0.6.0.dist-info/METADATA
proteus_runtime-0.6.0.dist-info/WHEEL
proteus_runtime-0.6.0.dist-info/RECORD
