Metadata-Version: 2.1
Name: proteus-runtime
Version: 0.6.0
Summary: 
Requires-Python: >=3.12,<3.13
Classifier: Programming Language :: Python :: 3
Classifier: Programming Language :: Python :: 3.12
Requires-Dist: azure-storage-blob (>=12.14.1,<13.0.0)
Requires-Dist: envclasses (>=0.3.1,<0.4.0)
Requires-Dist: multipart (>=0.2.4,<0.3.0)
Requires-Dist: numpy (>=2.0.0,<3.0.0)
Requires-Dist: parglare (==0.18)
Requires-Dist: poethepoet (>=0.27.0,<0.28.0)
Requires-Dist: pycryptodome (>=3.20,<4.0)
Requires-Dist: python-json-logger (>=2.0.4,<3.0.0)
Requires-Dist: python-slugify (>=8.0.1,<9.0.0)
Requires-Dist: requests (>=2.28.1,<3.0.0)
Requires-Dist: setuptools (>=70.0.0,<71.0.0)
Requires-Dist: tqdm (>=4.65.0,<5.0.0)
